gql_query_utils/__init__.py
gql_query_utils/utils.py
gql_query_utils-1.0.1.dist-info/METADATA
gql_query_utils-1.0.1.dist-info/WHEEL
gql_query_utils-1.0.1.dist-info/licenses/LICENSE
gql_query_utils-1.0.1.dist-info/RECORD
